MANIFEST.in
setup.py
mownfish/__init__.py
mownfish/db.py
mownfish/error.py
mownfish/http_server.py
mownfish/timer_task.py
mownfish.egg-info/PKG-INFO
mownfish.egg-info/SOURCES.txt
mownfish.egg-info/dependency_links.txt
mownfish.egg-info/entry_points.txt
mownfish.egg-info/top_level.txt
mownfish/cmd/__init__.py
mownfish/cmd/fishing.py
mownfish/cmd/mownfishd.py
mownfish/handlers/__init__.py
mownfish/handlers/base_handler.py
mownfish/handlers/index_handler.py
mownfish/handlers/statinfo_handler.py
mownfish/static/favicon.ico
mownfish/templates/etc/mownfish.conf
mownfish/templates/module/__init__.py
mownfish/templates/module/db.py
mownfish/templates/module/error.py
mownfish/templates/module/http_server.py.tmpl
mownfish/templates/module/timer_task.py.tmpl
mownfish/templates/module/cmd/__init__.py
mownfish/templates/module/cmd/mownfishd.py.tmpl
mownfish/templates/module/handlers/__init__.py.tmpl
mownfish/templates/module/handlers/base_handler.py.tmpl
mownfish/templates/module/handlers/index_handler.py.tmpl
mownfish/templates/module/handlers/statinfo_handler.py.tmpl
mownfish/templates/module/static/favicon.ico
mownfish/templates/module/util/__init__.py
mownfish/templates/module/util/commonutils.py
mownfish/templates/module/util/config.py.tmpl
mownfish/templates/module/util/log.py.tmpl
mownfish/templates/module/util/multiprocesslogging.py
mownfish/util/__init__.py
mownfish/util/commonutils.py
mownfish/util/config.py
mownfish/util/log.py
mownfish/util/multiprocesslogging.py