Metadata-Version: 1.1
Name: mownfish
Version: 3.1.3
Summary: A Tornado Productional Skeleton
Home-page: https://github.com/ethan-zhang/mownfish
Author: Ethan-Zhang
Author-email: unpeeled_onion@outlook.com
License: http://www.apache.org/licenses/LICENSE-2.0
Download-URL: https://github.com/Ethan-Zhang/mownfish/tree/v3.1
Keywords: tornado
Platform: UNKNOWN
